{"K":[[557,0,256.5],[0,557,256.5],[0,0,1]],"R":[[1,0,0],[0,-0.8678522,0.4968225],[0,-0.4968225,-0.8678522]],"t":[-1.39,0.2115668,6.977123],"minDepth":4.923697,"maxDepth":8.08576,"objects":[{"color":"leather","shape":"matt_green_sphere","size":"0.5719112","position":[1.767763,0.5359556,0.6081749,]},{"color":"laminate_floor","shape":"matt_pink_sphere","size":"0.8075499","position":[2.633014,0.653775,-1.724168,]},{"color":"green_metal_rust","shape":"Smooth_Cube_Green","size":"0.7539818","position":[0.356454,0.6269909,1.166309,]},{"color":"leather","shape":"matt_pink_sphere","size":"0.4483017","position":[1.461896,0.4741509,-0.9680654,]}]}