{"K":[[557,0,256.5],[0,557,256.5],[0,0,1]],"R":[[1,0,0],[0,-0.8678522,0.4968225],[0,-0.4968225,-0.8678522]],"t":[-1.39,0.2115668,6.977123],"minDepth":4.674337,"maxDepth":8.384094,"objects":[{"color":"leather","shape":"Smooth_Cube_Pink","size":"0.6109889","position":[2.143704,0.5554944,-1.893607,]},{"color":"laminate_floor","shape":"matt_pink_sphere","size":"0.6364835","position":[-0.4773364,0.5682418,1.63518,]},{"color":"green_metal_rust","shape":"matt_green_sphere","size":"0.709942","position":[-0.4916059,0.6049711,-1.533712,]},{"color":"leather","shape":"Smooth_Cube_Pink","size":"0.5435688","position":[0.810604,0.5217844,0.8987857,]}]}